{"references": [], "citations": {"nonIeeeCitationCount": "0", "contentType": "periodicals", "mlTime": "PT0.01616S", "paperCitations": {}, "patentCitationCount": "0", "formulaStrippedArticleTitle": "Construction of a paper-disk drive", "publisher": "IET", "lastupdate": "2014-11-03T13:49:33", "title": "Construction of a paper-disk drive", "isEarlyAccess": false, "mediaPath": "/mediastore/IEEE/content/media/5344685/5345107/5345110", "ieeeCitationCount": "0", "publicationNumber": "5344685"}, "details": {"volume": "1985", "isJournal": true, "copyrightOwner": "The Institution of Electrical Engineers", "isConference": false, "subType": " IEE Periodical", "isSMPTE": false, "lastupdate": "2014-11-03T13:49:33", "chronOrPublicationDate": "Autumn 1985", "pubLink": "/xpl/RecentIssue.jsp?punumber=5344685", "contentType": "periodicals", "isCustomDenial": false, "ephemeraFlag": "false", "mediaPath": "/mediastore/IEEE/content/media/5344685/5345107/5345110", "publicationTitle": "Electronic Systems News", "articleNumber": "5345110", "userInfo": {"fileCabinetContent": false, "guest": false, "showGet802Link": false, "individual": false, "showOpenUrlLink": false, "showPatentCitations": true, "institute": false, "subscribedContent": false, "fileCabinetUser": false, "member": false}, "startPage": "17", "rightsLink": "http://s100.copyright.com/AppDispatchServlet?publisherName=ieee&publication=0265-0096&title=Construction+of+a+paper-disk+drive&isbn=&publicationDate=Autumn+1985&author=&ContentID=10.1049/esn.1985.0068&orderBeanReset=true&startPage=17&endPage=18&volumeNum=1985&issueNum=3", "openAccessFlag": "no", "standardTitle": "Construction of a paper-disk drive", "title": "Construction of a paper-disk drive", "allowComments": false, "articleId": "5345110", "isACM": false, "pdfPath": "/iel5/5344685/5345107/05345110.pdf", "publicationDate": "Autumn 1985", "isOpenAccess": false, "persistentLink": "http://ieeexplore.ieee.org/servlet/opac?punumber=5344685", "copyrightYear": "1981-1989", "isNumber": "5345107", "issue": "3", "displayPublicationTitle": "Electronic Systems News", "citationCount": "0", "issn": [{"format": "Print ISSN", "value": "0265-0096"}], "issueLink": "/xpl/tocresult.jsp?isnumber=5345107", "formulaStrippedArticleTitle": "Construction of a paper-disk drive", "isStaticHtml": false, "isStandard": false, "accessionNumber": "", "publicationNumber": "5344685", "isDynamicHtml": false, "sections": {"abstract": "false", "multimedia": "false", "disclaimer": "false", "authors": "false", "footnotes": "false", "figures": "false", "citedby": "", "keywords": "false", "references": "false"}, "conferenceDate": " ", "isPromo": false, "previewImage": "/xploreAssets/images/absImages/05345110.png", "isBook": false, "isEphemera": false, "htmlAbstractLink": "/document/5345110/", "mlTime": "PT0.0218S", "isNotDynamicOrStatic": true, "isFreeDocument": false, "doi": "10.1049/esn.1985.0068", "publisher": "IET", "isEarlyAccess": false, "endPage": "18"}, "arnumber": "5345110"}