{"references": [], "citations": {"nonIeeeCitationCount": "0", "contentType": "periodicals", "mlTime": "PT0.021582S", "paperCitations": {}, "patentCitationCount": "0", "formulaStrippedArticleTitle": "Teaching pupils to fault find", "publisher": "IET", "lastupdate": "2014-10-14T11:01:11", "title": "Teaching pupils to fault find", "isEarlyAccess": false, "mediaPath": "/mediastore/IEEE/content/media/5344685/5344806/5344812", "ieeeCitationCount": "0", "publicationNumber": "5344685"}, "details": {"volume": "1988", "isJournal": true, "copyrightOwner": "The Institution of Electrical Engineers", "isConference": false, "subType": " IEE Periodical", "isSMPTE": false, "lastupdate": "2014-10-14T11:01:11", "chronOrPublicationDate": "Spring 1988", "pubLink": "/xpl/RecentIssue.jsp?punumber=5344685", "contentType": "periodicals", "isCustomDenial": false, "ephemeraFlag": "false", "mediaPath": "/mediastore/IEEE/content/media/5344685/5344806/5344812", "publicationTitle": "Electronic Systems News", "articleNumber": "5344812", "userInfo": {"fileCabinetContent": false, "guest": false, "showGet802Link": false, "individual": false, "showOpenUrlLink": false, "showPatentCitations": true, "institute": false, "subscribedContent": false, "fileCabinetUser": false, "member": false}, "startPage": "11", "rightsLink": "http://s100.copyright.com/AppDispatchServlet?publisherName=ieee&publication=0265-0096&title=Teaching+pupils+to+fault+find&isbn=&publicationDate=Spring+1988&author=Jenny+Tizard&ContentID=10.1049/esn.1988.0004&orderBeanReset=true&startPage=11&volumeNum=1988&issueNum=1", "openAccessFlag": "no", "standardTitle": "Teaching pupils to fault find", "title": "Teaching pupils to fault find", "allowComments": false, "articleId": "5344812", "isACM": false, "pdfPath": "/iel5/5344685/5344806/05344812.pdf", "publicationDate": "Spring 1988", "isOpenAccess": false, "persistentLink": "http://ieeexplore.ieee.org/servlet/opac?punumber=5344685", "copyrightYear": "1981-1989", "isNumber": "5344806", "issue": "1", "displayPublicationTitle": "Electronic Systems News", "citationCount": "0", "issn": [{"format": "Print ISSN", "value": "0265-0096"}], "issueLink": "/xpl/tocresult.jsp?isnumber=5344806", "formulaStrippedArticleTitle": "Teaching pupils to fault find", "authors": [{"affiliation": "Bradford and Ilkley Community College, Bradford, UK", "name": "Jenny Tizard"}], "isStaticHtml": false, "isStandard": false, "accessionNumber": "", "publicationNumber": "5344685", "isDynamicHtml": false, "sections": {"abstract": "false", "multimedia": "false", "disclaimer": "false", "authors": "true", "footnotes": "false", "figures": "false", "citedby": "", "keywords": "false", "references": "false"}, "conferenceDate": " ", "isPromo": false, "previewImage": "/xploreAssets/images/absImages/05344812.png", "isBook": false, "isEphemera": false, "htmlAbstractLink": "/document/5344812/", "mlTime": "PT0.031738S", "isNotDynamicOrStatic": true, "isFreeDocument": false, "doi": "10.1049/esn.1988.0004", "publisher": "IET", "isEarlyAccess": false}, "arnumber": "5344812"}